pigeomail/__init__.py
pigeomail/__version__.py
pigeomail/cmdline.py
pigeomail-0.0.8.data/data/LICENSE
pigeomail-0.0.8.dist-info/LICENSE
pigeomail-0.0.8.dist-info/METADATA
pigeomail-0.0.8.dist-info/WHEEL
pigeomail-0.0.8.dist-info/entry_points.txt
pigeomail-0.0.8.dist-info/top_level.txt
pigeomail-0.0.8.dist-info/RECORD
