Metadata-Version: 2.1
Name: pigeomail
Version: 0.0.8
Summary: ✨ Awesome email tookit that shines ✨
Home-page: https://github.com/szj2ys/pigeomail
Author: SZJ
Author-email: szj2ys@qq.com
License: MIT
Platform: UNKNOWN
Classifier: Development Status :: 3 - Alpha
Classifier: License :: OSI Approved :: MIT License
Classifier: Programming Language :: Python :: 3
Requires-Python: >=3.5.0
License-File: LICENSE
Requires-Dist: doger
